[
  {
    "timestamp":"2026-07-17T19:15:12Z",
    "commit":"b92492b6ab2d809349f1e5f10cc0097f0fdf822c",
    "ref":"main",
    "event":"merge",
    "pr_number":null,
    "target":"tdigest_healpix_o9_inline_mask",
    "aggregator":"tdigest",
    "grid_type":"healpix",
    "grid_size":"o9",
    "shard_key":5347395636851376137,
    "n_granules":66,
    "total_obs":3329701,
    "runtime_s":133.967773,
    "gb_seconds":535.871092,
    "cost_per_shard_usd":0.0071449836,
    "shard_area_km2":162.1455767863,
    "cost_per_100km2_usd":0.0044065239,
    "function_timeout_s":720,
    "worker_pct_timeout":0.1860663514,
    "memory_gb":4.0,
    "price_per_gb_sec":0.0000133334,
    "zagg_version":"0.1.dev1+gb92492b6a",
    "max_memory_mb":681.1328125,
    "codec":null,
    "read":null,
    "total_wall_s":137.8835365772,
    "setup_s":4.6825258732,
    "fanout_s":137.8835320473,
    "finalize_s":0.0000042915,
    "index_backend":"inline",
    "objects_total":12.0,
    "objects_expected":12.0,
    "store_layout":"flat"
  },
  {
    "timestamp":"2026-07-17T19:15:12Z",
    "commit":"b92492b6ab2d809349f1e5f10cc0097f0fdf822c",
    "ref":"main",
    "event":"merge",
    "pr_number":null,
    "target":"tdigest_healpix_o9_inline_nomask",
    "aggregator":"tdigest",
    "grid_type":"healpix",
    "grid_size":"o9",
    "shard_key":5347395636851376137,
    "n_granules":66,
    "total_obs":3329701,
    "runtime_s":118.086357,
    "gb_seconds":472.345428,
    "cost_per_shard_usd":0.0062979705,
    "shard_area_km2":162.1455767863,
    "cost_per_100km2_usd":0.0038841458,
    "function_timeout_s":720,
    "worker_pct_timeout":0.1640088292,
    "memory_gb":4.0,
    "price_per_gb_sec":0.0000133334,
    "zagg_version":"0.1.dev1+gb92492b6a",
    "max_memory_mb":697.17578125,
    "codec":null,
    "read":null,
    "total_wall_s":121.5294444561,
    "setup_s":4.3975930214,
    "fanout_s":121.5294394493,
    "finalize_s":0.00000453,
    "index_backend":"inline",
    "objects_total":10.0,
    "objects_expected":10.0,
    "store_layout":"flat"
  },
  {
    "timestamp":"2026-07-17T19:15:12Z",
    "commit":"b92492b6ab2d809349f1e5f10cc0097f0fdf822c",
    "ref":"main",
    "event":"merge",
    "pr_number":null,
    "target":"tdigest_healpix_o9_sidecar_mask",
    "aggregator":"tdigest",
    "grid_type":"healpix",
    "grid_size":"o9",
    "shard_key":5347395636851376137,
    "n_granules":66,
    "total_obs":3329701,
    "runtime_s":107.609083,
    "gb_seconds":430.436332,
    "cost_per_shard_usd":0.0057391798,
    "shard_area_km2":162.1455767863,
    "cost_per_100km2_usd":0.0035395229,
    "function_timeout_s":720,
    "worker_pct_timeout":0.1494570597,
    "memory_gb":4.0,
    "price_per_gb_sec":0.0000133334,
    "zagg_version":"0.1.dev1+gb92492b6a",
    "max_memory_mb":618.8828125,
    "codec":null,
    "read":null,
    "total_wall_s":111.990676403,
    "setup_s":3.6947345734,
    "fanout_s":111.9906694889,
    "finalize_s":0.0000061989,
    "index_backend":"sidecar",
    "objects_total":12.0,
    "objects_expected":12.0,
    "store_layout":"flat"
  },
  {
    "timestamp":"2026-07-17T19:15:12Z",
    "commit":"b92492b6ab2d809349f1e5f10cc0097f0fdf822c",
    "ref":"main",
    "event":"merge",
    "pr_number":null,
    "target":"tdigest_healpix_o9_sidecar_nomask",
    "aggregator":"tdigest",
    "grid_type":"healpix",
    "grid_size":"o9",
    "shard_key":5347395636851376137,
    "n_granules":66,
    "total_obs":3329701,
    "runtime_s":102.443502,
    "gb_seconds":409.774008,
    "cost_per_shard_usd":0.0054636808,
    "shard_area_km2":162.1455767863,
    "cost_per_100km2_usd":0.0033696144,
    "function_timeout_s":720,
    "worker_pct_timeout":0.1422826417,
    "memory_gb":4.0,
    "price_per_gb_sec":0.0000133334,
    "zagg_version":"0.1.dev1+gb92492b6a",
    "max_memory_mb":634.32421875,
    "codec":null,
    "read":null,
    "total_wall_s":108.3552248478,
    "setup_s":5.2122621536,
    "fanout_s":108.3552186489,
    "finalize_s":0.0000054836,
    "index_backend":"sidecar",
    "objects_total":10.0,
    "objects_expected":10.0,
    "store_layout":"flat"
  }
]